{
  "id": "pattern-runner",
  "title": "Pattern Runner (Game Commitment)",
  "description": "SHA-256 commitment of rhythm streak actions, score, and wallet. Generated by completing the mini game.",
  "smartWallet": "CBNQ2X6T7JXK5B2M5AGPSZ5XKQZV6K7W2Q4R2J5P6K3X6ZL7PRX7G5QY",
  "network": "stellar-testnet",
  "scheme": "SHA-256 commit-reveal",
  "method": "sha256(JSON.stringify({wallet, gameId, level, score, actionHash, salt}))",
  "sampleData": {
    "streakLength": 6,
    "actionHash": "sha256 of beat actions (32 bytes)",
    "commitment": "sha256 of full game state + salt (32 bytes)"
  },
  "outputs": {
    "attestation": "game-committed",
    "badge": "pattern-runner"
  },
  "verification": "Recompute sha256 from wallet + game state + salt and compare to stored commitment.",
  "generatedAt": "2026-02-07T00:00:00.000Z",
  "source": "smol labs / the farm",
  "note": "Sample format. Real commitments are generated client-side by completing the Pattern Runner mini game."
}
